polymap/__init__.py
polymap/efs.py
polymap/key.py
polymap/sql.py
polymap-0.0.2.dist-info/LICENSE
polymap-0.0.2.dist-info/METADATA
polymap-0.0.2.dist-info/WHEEL
polymap-0.0.2.dist-info/top_level.txt
polymap-0.0.2.dist-info/RECORD
