Metadata-Version: 2.1
Name: polymap
Version: 0.0.2
Summary: A Python package for managing web resources.
Author-email: joumaico <joumaico@gmx.com>
License: MIT License
Project-URL: Homepage, https://github.com/joumaico/polymap
Classifier: License :: OSI Approved :: MIT License
Classifier: Programming Language :: Python
Classifier: Programming Language :: Python :: 3
Requires-Python: >=3.10
License-File: LICENSE
